{
  "name": "post_pics/ed9e32cd-d123-41a0-80e8-b26af9a50e09/9791571d-1979-4624-9d82-f54e706e3100.jpg",
  "bucket": "gym-buddy-9ab39.firebasestorage.app",
  "metageneration": 1,
  "generation": 1732315526250,
  "contentType": "image/jpg",
  "storageClass": "STANDARD",
  "contentDisposition": "inline",
  "downloadTokens": [
    "9287ead7-ead1-4806-96db-f440db14844c"
  ],
  "etag": "KN8cM7KnsDf58jEjQMO7x4l+2CQ",
  "customMetadata": {},
  "timeCreated": "2024-11-22T22:45:26.251Z",
  "updated": "2024-11-22T22:45:26.251Z",
  "size": 570991,
  "md5Hash": "uR1QdjpklB8eitzYBhV0uA==",
  "crc32c": "74644107"
}